Cl1pAPI/Cl1pAPI.py
Cl1pAPI/__init__.py
Cl1pAPI-0.0.dist-info/METADATA
Cl1pAPI-0.0.dist-info/WHEEL
Cl1pAPI-0.0.dist-info/top_level.txt
Cl1pAPI-0.0.dist-info/RECORD
