Metadata-Version: 2.1
Name: Cl1pAPI
Version: 0.0
